[
  {
    "schema_version": "1.0.0",
    "source_id": "SRC-0001",
    "title": "Riley v. California, 573 U.S. 373 (2014) — full opinion (Cornell Legal Information Institute)",
    "author": "Supreme Court of the United States (opinion of the Court by Roberts, C.J.)",
    "organization": "Cornell Law School — Legal Information Institute",
    "publication_date": "2014-06-25",
    "accessed_at": "2026-06-20T00:00:00+00:00",
    "reference": "https://www.law.cornell.edu/supremecourt/text/13-132",
    "source_type": "primary",
    "authority": 5,
    "directness": 5,
    "independence": 5,
    "recency": 5,
    "bias_or_interest": "Primary judicial record; Cornell LII is a neutral redistributor.",
    "relevant_locations": ["Syllabus", "Opinion of the Court (Roberts, C.J.)", "Concurrence (Alito, J., in part and in the judgment)"],
    "quotation_note": "Public-domain U.S. government work; short attributed quotes ('get a warrant', 'the privacies of life') are safe.",
    "rights_note": "Opinion text is public domain. Cite Cornell LII as the access source.",
    "content_hash": null,
    "notes": "Primary opinion (No. 13-132), decided with United States v. Wurie (No. 13-212). Confirms 9-0 judgment, Jun 25 2014, Roberts; Chimel rationales; quantitative+qualitative difference. Capture durable hash before publish."
  },
  {
    "schema_version": "1.0.0",
    "source_id": "SRC-0002",
    "title": "Riley v. California, 573 U.S. 373 (2014) — Justia case record",
    "author": null,
    "organization": "Justia",
    "publication_date": null,
    "accessed_at": "2026-06-20T00:00:00+00:00",
    "reference": "https://supreme.justia.com/cases/federal/us/573/373",
    "source_type": "institutional",
    "authority": 4,
    "directness": 3,
    "independence": 4,
    "recency": 4,
    "bias_or_interest": "Legal database; secondary summary of the primary record.",
    "relevant_locations": ["Syllabus", "Facts", "Holding", "Vote"],
    "quotation_note": "Summarize; do not copy long passages.",
    "rights_note": "Metadata/summary reference only.",
    "content_hash": null,
    "notes": "Cross-check for vote, date, facts (San Diego stop; warrantless smartphone search; gang/shooting link)."
  },
  {
    "schema_version": "1.0.0",
    "source_id": "SRC-0003",
    "title": "Katz v. United States, 389 U.S. 347 (1967) — full opinion (Cornell Legal Information Institute)",
    "author": "Supreme Court of the United States (opinion of the Court by Stewart, J.; concurrence by Harlan, J.)",
    "organization": "Cornell Law School — Legal Information Institute",
    "publication_date": "1967-12-18",
    "accessed_at": "2026-06-20T00:00:00+00:00",
    "reference": "https://www.law.cornell.edu/supremecourt/text/389/347",
    "source_type": "primary",
    "authority": 5,
    "directness": 5,
    "independence": 5,
    "recency": 4,
    "bias_or_interest": "Primary judicial record (background principle).",
    "relevant_locations": ["Opinion of the Court ('people, not places')", "Harlan, J., concurrence (reasonable expectation of privacy)"],
    "quotation_note": "Public-domain; short attributed quote ('protects people, not places') is safe.",
    "rights_note": "Public domain. Background source for the privacy principle Riley builds on.",
    "content_hash": null,
    "notes": "Used only for the background 'people, not places' / reasonable-expectation principle woven into Riley."
  }
]
