[
  {
    "schema_version": "1.0.0",
    "source_id": "SRC-0001",
    "title": "Isabella Stewart Gardner Museum Heist — FBI Famous Cases",
    "author": "Federal Bureau of Investigation",
    "organization": "FBI",
    "publication_date": "2013-03-18",
    "accessed_at": "2026-06-29T00:00:00+00:00",
    "reference": "https://www.fbi.gov/history/famous-cases/isabella-stewart-gardner-museum-heist",
    "source_type": "primary",
    "authority": 5,
    "directness": 5,
    "independence": 5,
    "recency": 4,
    "bias_or_interest": "Investigating agency; authoritative on the heist facts, count, value characterization, reward, unsolved status.",
    "relevant_locations": [
      "March 18, 1990; two men dressed as Boston police; guard broke protocol",
      "Guards overpowered and tied up in the basement; 81 minutes; 13 works",
      "~$500 million estimate; 'largest property crime in U.S. history'",
      "Empty frames displayed; case still under investigation; $10M reward",
      "Vermeer 'The Concert' = most valuable unrecovered painting in the world"
    ],
    "quotation_note": "U.S. government work, public domain; short attributed quotes safe.",
    "rights_note": "Public domain (U.S. govt). Page bot-protected to automated fetch; confirm verbatim quotes on the live page before publish.",
    "content_hash": null,
    "notes": "PRIMARY FBI case page. Durable hash PENDING (bot wall)."
  },
  {
    "schema_version": "1.0.0",
    "source_id": "SRC-0002",
    "title": "The Theft — Isabella Stewart Gardner Museum (official theft page)",
    "author": "Isabella Stewart Gardner Museum",
    "organization": "Isabella Stewart Gardner Museum",
    "publication_date": "2020-03-01",
    "accessed_at": "2026-06-29T00:00:00+00:00",
    "reference": "https://www.gardnermuseum.org/about/theft",
    "source_type": "primary",
    "authority": 5,
    "directness": 5,
    "independence": 4,
    "recency": 4,
    "bias_or_interest": "The victim institution; authoritative on the works, the timeline, the empty frames, and the reward.",
    "relevant_locations": [
      "Thieves entered ~employee entrance; guards restrained; departed 2:45 a.m., two car trips",
      "Paintings cut from frames (the two large Rembrandts); Manet frame left behind",
      "List of all 13 stolen works; Vermeer 'The Concert' most valuable",
      "Empty frames remain on display; $10M reward"
    ],
    "quotation_note": "Quote sparingly with attribution; museum-authored.",
    "rights_note": "Museum content; paraphrase, short attributed quotes. HTML bot-protected; PDF press releases fetched directly.",
    "content_hash": null,
    "notes": "PRIMARY museum theft page + the 13-works list (Google Arts & Culture museum-authored). Durable hash PENDING."
  },
  {
    "schema_version": "1.0.0",
    "source_id": "SRC-0003",
    "title": "FBI/DOJ March 2013 announcement: thieves believed identified; publicity campaign; trace to CT & Philadelphia",
    "author": "FBI Boston / U.S. Attorney's Office, District of Massachusetts",
    "organization": "FBI / DOJ (USAO-MA)",
    "publication_date": "2013-03-18",
    "accessed_at": "2026-06-29T00:00:00+00:00",
    "reference": "https://www.fbi.gov/news/stories/2013/march/reward-offered-for-return-of-stolen-gardner-museum-artwork",
    "source_type": "primary",
    "authority": 5,
    "directness": 4,
    "independence": 4,
    "recency": 4,
    "bias_or_interest": "Investigating agency statement; content confirmed by multiple outlets (page blocked to automated fetch).",
    "relevant_locations": [
      "SAC DesLauriers: high confidence the thieves were identified; criminal organization, Mid-Atlantic & New England",
      "FBI declined to name individuals",
      "Art transported to Connecticut and the Philadelphia area; offered for sale ~a decade earlier; current location unknown",
      "Statute of limitations on the theft expired; recovery focus / immunity considered"
    ],
    "quotation_note": "Attribute to the FBI/U.S. Attorney; confirm verbatim on live page before publish.",
    "rights_note": "Public domain (U.S. govt). Content verified via WBUR / Center for Art Law; lock wording before broadcast.",
    "content_hash": null,
    "notes": "PRIMARY 2013 announcement (A-content / B-verified). Durable hash PENDING (bot wall)."
  },
  {
    "schema_version": "1.0.0",
    "source_id": "SRC-0004",
    "title": "Gardner Museum press release (Jan 2018): $10M reward extended; works unsaleable ('only buyer')",
    "author": "Isabella Stewart Gardner Museum (Board President Steve Kidder)",
    "organization": "Isabella Stewart Gardner Museum",
    "publication_date": "2018-01-01",
    "accessed_at": "2026-06-29T00:00:00+00:00",
    "reference": "https://www.gardnermuseum.org/about/theft",
    "source_type": "primary",
    "authority": 5,
    "directness": 5,
    "independence": 4,
    "recency": 4,
    "bias_or_interest": "Victim institution; authoritative on reward history and the works' unsaleability.",
    "relevant_locations": [
      "Reward $10M (raised May 2017), deadline extended Jan 2018 with no current expiration",
      "'We are the only buyer for these works' (value is an estimate, not a market price)",
      "'largest art heist in history' characterization"
    ],
    "quotation_note": "Short attributed quotes; museum PDF press release.",
    "rights_note": "Museum content; paraphrase / short attributed quotes.",
    "content_hash": null,
    "notes": "PRIMARY reward history + unsaleability. Durable hash PENDING."
  },
  {
    "schema_version": "1.0.0",
    "source_id": "SRC-0005",
    "title": "WBUR — 'FBI Says It Has Identified Thieves Who Stole Gardner Museum Art' (Mar 18, 2013)",
    "author": "WBUR newsroom",
    "organization": "WBUR (Boston NPR)",
    "publication_date": "2013-03-18",
    "accessed_at": "2026-06-29T00:00:00+00:00",
    "reference": "https://www.wbur.org/news/2013/03/18/gardner-museum-art-fbi",
    "source_type": "secondary",
    "authority": 4,
    "directness": 4,
    "independence": 5,
    "recency": 4,
    "bias_or_interest": "Independent journalism; corroborates FBI 2013 statements + immunity (Ortiz) and trace to Philadelphia.",
    "relevant_locations": [
      "DesLauriers quote on identified thieves / criminal organization",
      "U.S. Attorney Carmen Ortiz on immunity possibility",
      "Statute of limitations expired; recovery focus"
    ],
    "quotation_note": "Attribute spoken official remarks; single-outlet quotes flagged.",
    "rights_note": "Third-party news; paraphrase + short attributed quotes.",
    "content_hash": null,
    "notes": "SECONDARY verification of the blocked FBI/DOJ 2013 release. Durable hash PENDING."
  },
  {
    "schema_version": "1.0.0",
    "source_id": "SRC-0006",
    "title": "WBUR — 'With Gardner Heist Suspects Dead, FBI Focuses On Finding Art' (Aug 7, 2015)",
    "author": "WBUR newsroom",
    "organization": "WBUR (Boston NPR)",
    "publication_date": "2015-08-07",
    "accessed_at": "2026-06-29T00:00:00+00:00",
    "reference": "https://www.wbur.org/news/2015/08/06/gardner-museum-heist-update",
    "source_type": "secondary",
    "authority": 4,
    "directness": 4,
    "independence": 5,
    "recency": 4,
    "bias_or_interest": "Independent journalism; FBI assistant SAC Kowenhoven on the two thieves being deceased.",
    "relevant_locations": [
      "FBI: the two who committed the heist are identified and 'both those individuals are deceased'; FBI declined to name them"
    ],
    "quotation_note": "Attribute to the FBI official; do not name individuals the FBI did not name.",
    "rights_note": "Third-party news; paraphrase / short attributed quotes.",
    "content_hash": null,
    "notes": "SECONDARY for 'suspects deceased, unnamed.' Durable hash PENDING."
  },
  {
    "schema_version": "1.0.0",
    "source_id": "SRC-0007",
    "title": "The Boston Globe — 'Whodunit? A list of the suspects in the Gardner Museum heist' (Feb 28, 2022)",
    "author": "The Boston Globe",
    "organization": "The Boston Globe",
    "publication_date": "2022-02-28",
    "accessed_at": "2026-06-29T00:00:00+00:00",
    "reference": "https://www.bostonglobe.com/2022/02/28/metro/whodunit-list-suspects-gardner-museum-heist/",
    "source_type": "secondary",
    "authority": 4,
    "directness": 3,
    "independence": 5,
    "recency": 4,
    "bias_or_interest": "Independent journalism; the source for named persons of interest + their living/deceased status + exact characterization.",
    "relevant_locations": [
      "Status + characterization of named persons (Abath, Turner, Connor, Donati, Reissfelder, DiMuzio, Merlino, Guarente, Gentile, etc.)",
      "Reissfelder/DiMuzio named by journalists, NOT the FBI",
      "Myles Connor was incarcerated on 1990-03-18; never charged"
    ],
    "quotation_note": "Use each person's exact hedge (suspect / person of interest / investigated / never charged). Never assert guilt of living persons.",
    "rights_note": "Third-party news; paraphrase only.",
    "content_hash": null,
    "notes": "SECONDARY for suspect names + status. CRITICAL for R2 wording. Durable hash PENDING."
  },
  {
    "schema_version": "1.0.0",
    "source_id": "SRC-0008",
    "title": "Encyclopaedia Britannica — 'Isabella Stewart Gardner Museum' (will terms; unsolved status)",
    "author": "Encyclopaedia Britannica",
    "organization": "Encyclopaedia Britannica",
    "publication_date": "2024-01-01",
    "accessed_at": "2026-06-29T00:00:00+00:00",
    "reference": "https://www.britannica.com/topic/Gardner-Museum",
    "source_type": "secondary",
    "authority": 4,
    "directness": 3,
    "independence": 5,
    "recency": 4,
    "bias_or_interest": "Reference work; corroborates the will-arrangement rule and unsolved status.",
    "relevant_locations": [
      "Gardner's will: keep the collection as she arranged it (nothing added/removed/rearranged)",
      "Heist remains unsolved"
    ],
    "quotation_note": "Paraphrase; note 2009 court ruling relaxed strict terms (Renzo Piano wing 2012).",
    "rights_note": "Third-party reference; paraphrase.",
    "content_hash": null,
    "notes": "SECONDARY for the will terms (frame the 'empty frames' reason carefully). Durable hash PENDING."
  },
  {
    "schema_version": "1.0.0",
    "source_id": "SRC-0009",
    "title": "WBUR — 'Here Are The 13 Artworks Stolen From The Gardner Museum' (Aug 20, 2018)",
    "author": "WBUR newsroom",
    "organization": "WBUR (Boston NPR)",
    "publication_date": "2018-08-20",
    "accessed_at": "2026-06-29T00:00:00+00:00",
    "reference": "https://www.wbur.org/news/2018/08/20/gardner-museum-stolen-art-list",
    "source_type": "secondary",
    "authority": 4,
    "directness": 4,
    "independence": 5,
    "recency": 4,
    "bias_or_interest": "Independent journalism; corroborates the list of 13 works and descriptive details (e.g., small Rembrandt self-portrait etching size).",
    "relevant_locations": [
      "Enumerated 13 works (artists + titles)",
      "Rembrandt's only seascape; the small self-portrait; the five Degas; the Gu beaker; the Napoleonic eagle finial"
    ],
    "quotation_note": "Paraphrase the art list; cross-checked with FBI + museum.",
    "rights_note": "Third-party news; paraphrase.",
    "content_hash": null,
    "notes": "SECONDARY corroboration of the works list. Durable hash PENDING."
  },
  {
    "schema_version": "1.0.0",
    "source_id": "SRC-0010",
    "title": "AP via PBS NewsHour — 'What to know about the world's largest art heist from a Boston museum'",
    "author": "Leah Willingham (Associated Press)",
    "organization": "Associated Press / PBS NewsHour",
    "publication_date": "2026-04-26",
    "accessed_at": "2026-06-29T00:00:00+00:00",
    "reference": "https://www.pbs.org/newshour/arts/what-to-know-about-the-worlds-largest-art-heist-from-a-boston-museum",
    "source_type": "secondary",
    "authority": 4,
    "directness": 3,
    "independence": 5,
    "recency": 5,
    "bias_or_interest": "Independent journalism; recent recap (post-St-Patrick's-Day timing, duct tape, restraint).",
    "relevant_locations": [
      "Timing just after St. Patrick's Day",
      "Guards restrained; heads wrapped in duct tape",
      "Largest art heist framing; reward; unsolved"
    ],
    "quotation_note": "Paraphrase; recent secondary recap.",
    "rights_note": "Third-party news; paraphrase.",
    "content_hash": null,
    "notes": "SECONDARY recent recap. Durable hash PENDING."
  },
  {
    "schema_version": "1.0.0",
    "source_id": "SRC-0011",
    "title": "CBS News — 'The heist of the century' (Dec 6, 2015)",
    "author": "CBS News / 60 Minutes",
    "organization": "CBS News",
    "publication_date": "2015-12-06",
    "accessed_at": "2026-06-29T00:00:00+00:00",
    "reference": "https://www.cbsnews.com/news/the-heist-of-the-century/",
    "source_type": "secondary",
    "authority": 4,
    "directness": 3,
    "independence": 5,
    "recency": 3,
    "bias_or_interest": "Independent journalism; heist window (~1:24-2:45 a.m.) and the Blue Room motion-sensor anomaly (per security chief Amore).",
    "relevant_locations": [
      "Entry ~1:24 a.m.; departure 2:45 a.m.",
      "No motion sensor recorded anyone but a guard entering the Blue Room where 'Chez Tortoni' hung"
    ],
    "quotation_note": "Attribute the anomaly to Amore/CBS.",
    "rights_note": "Third-party news; paraphrase.",
    "content_hash": null,
    "notes": "SECONDARY for the timeline window + Blue Room anomaly. Durable hash PENDING."
  }
]
