{
  "episode_id": "PD-2026-002-gideon",
  "voice_id": "nPczCjzI2devNBz1zQrb",
  "model_id": "eleven_multilingual_v2",
  "generated_total_seconds": 572.6,
  "chunks": [
    {
      "chunk_id": "VC-0001",
      "file": "VC-0001.mp3",
      "delivery": "intense",
      "seconds": 6.316
    },
    {
      "chunk_id": "VC-0002",
      "file": "VC-0002.mp3",
      "delivery": "building",
      "seconds": 23.684
    },
    {
      "chunk_id": "VC-0003",
      "file": "VC-0003.mp3",
      "delivery": "calm",
      "seconds": 47.09
    },
    {
      "chunk_id": "VC-0004",
      "file": "VC-0004.mp3",
      "delivery": "calm",
      "seconds": 20.294
    },
    {
      "chunk_id": "VC-0005",
      "file": "VC-0005.mp3",
      "delivery": "calm",
      "seconds": 18.669
    },
    {
      "chunk_id": "VC-0006",
      "file": "VC-0006.mp3",
      "delivery": "building",
      "seconds": 27.121
    },
    {
      "chunk_id": "VC-0007",
      "file": "VC-0007.mp3",
      "delivery": "building",
      "seconds": 14.071
    },
    {
      "chunk_id": "VC-0008",
      "file": "VC-0008.mp3",
      "delivery": "building",
      "seconds": 10.403
    },
    {
      "chunk_id": "VC-0009",
      "file": "VC-0009.mp3",
      "delivery": "calm",
      "seconds": 13.607
    },
    {
      "chunk_id": "VC-0010",
      "file": "VC-0010.mp3",
      "delivery": "calm",
      "seconds": 19.876
    },
    {
      "chunk_id": "VC-0011",
      "file": "VC-0011.mp3",
      "delivery": "building",
      "seconds": 31.161
    },
    {
      "chunk_id": "VC-0012",
      "file": "VC-0012.mp3",
      "delivery": "building",
      "seconds": 19.273
    },
    {
      "chunk_id": "VC-0013",
      "file": "VC-0013.mp3",
      "delivery": "intense",
      "seconds": 20.759
    },
    {
      "chunk_id": "VC-0014",
      "file": "VC-0014.mp3",
      "delivery": "building",
      "seconds": 10.913
    },
    {
      "chunk_id": "VC-0015",
      "file": "VC-0015.mp3",
      "delivery": "intense",
      "seconds": 13.235
    },
    {
      "chunk_id": "VC-0016",
      "file": "VC-0016.mp3",
      "delivery": "building",
      "seconds": 28.282
    },
    {
      "chunk_id": "VC-0017",
      "file": "VC-0017.mp3",
      "delivery": "building",
      "seconds": 21.13
    },
    {
      "chunk_id": "VC-0018",
      "file": "VC-0018.mp3",
      "delivery": "intense",
      "seconds": 21.13
    },
    {
      "chunk_id": "VC-0019",
      "file": "VC-0019.mp3",
      "delivery": "building",
      "seconds": 8.406
    },
    {
      "chunk_id": "VC-0020",
      "file": "VC-0020.mp3",
      "delivery": "building",
      "seconds": 19.923
    },
    {
      "chunk_id": "VC-0021",
      "file": "VC-0021.mp3",
      "delivery": "building",
      "seconds": 15.604
    },
    {
      "chunk_id": "VC-0022",
      "file": "VC-0022.mp3",
      "delivery": "intense",
      "seconds": 25.681
    },
    {
      "chunk_id": "VC-0023",
      "file": "VC-0023.mp3",
      "delivery": "calm",
      "seconds": 25.356
    },
    {
      "chunk_id": "VC-0024",
      "file": "VC-0024.mp3",
      "delivery": "building",
      "seconds": 31.858
    },
    {
      "chunk_id": "VC-0025",
      "file": "VC-0025.mp3",
      "delivery": "calm",
      "seconds": 14.025
    },
    {
      "chunk_id": "VC-0026",
      "file": "VC-0026.mp3",
      "delivery": "calm",
      "seconds": 20.991
    },
    {
      "chunk_id": "VC-0027",
      "file": "VC-0027.mp3",
      "delivery": "intense",
      "seconds": 18.204
    },
    {
      "chunk_id": "VC-0028",
      "file": "VC-0028.mp3",
      "delivery": "calm",
      "seconds": 25.542
    }
  ]
}
