{
  "schema_version": "1.0.0",
  "episode_id": "PD-2026-010-kelo",
  "revision": "v001",
  "kind": "ledger",
  "assets": [
    {
      "asset_id": "pexels_v_31008269",
      "asset_type": "video",
      "source": "pexels",
      "source_url": "https://www.pexels.com/video/aerial-view-of-suburban-greenery-and-rural-road-31008269/",
      "author": "Toàn BDS",
      "license": "Pexels License",
      "commercial_use": "allowed",
      "file": "artifact://episodes/PD-2026-010-kelo/05_stock/candidates/pexels_v_31008269.mp4",
      "sha256": "sha256:17eabe2d5bc32e42b2bc9840a783f5c7c0db096502d8acb7f62427b1366e1411",
      "bytes": 31356145,
      "query": "small house standing alone amid cleared lots",
      "depicts": "small house standing alone amid cleared lots",
      "fetched_at": "",
      "used_in_spans": [
        "SPN-0001"
      ]
    },
    {
      "asset_id": "pexels_v_2801656",
      "asset_type": "video",
      "source": "pexels",
      "source_url": "https://www.pexels.com/video/drone-footage-of-a-residential-community-2801656/",
      "author": "K",
      "license": "Pexels License",
      "commercial_use": "allowed",
      "file": "artifact://episodes/PD-2026-010-kelo/05_stock/candidates/pexels_v_2801656.mp4",
      "sha256": "sha256:d64aafce42f63573553d0e203c7d90b4c57447b6d00cd90591db244e7aa1dd9a",
      "bytes": 33563122,
      "query": "small house standing alone amid cleared lots",
      "depicts": "small house standing alone amid cleared lots",
      "fetched_at": "",
      "used_in_spans": [
        "SPN-0001"
      ]
    },
    {
      "asset_id": "pexels_v_5362813",
      "asset_type": "video",
      "source": "pexels",
      "source_url": "https://www.pexels.com/video/small-building-by-the-road-5362813/",
      "author": "Adrien JACTA",
      "license": "Pexels License",
      "commercial_use": "allowed",
      "file": "artifact://episodes/PD-2026-010-kelo/05_stock/candidates/pexels_v_5362813.mp4",
      "sha256": "sha256:38315f907fc2584144aa1511e4b70da3436f75f24db2269fbf7b98fff2a75142",
      "bytes": 4041579,
      "query": "small house standing alone amid cleared lots",
      "depicts": "small house standing alone amid cleared lots",
      "fetched_at": "",
      "used_in_spans": [
        "SPN-0001"
      ]
    },
    {
      "asset_id": "pexels_i_15263342",
      "asset_type": "image",
      "source": "pexels",
      "source_url": "https://www.pexels.com/photo/a-house-in-winter-15263342/",
      "author": "Tom Fisk",
      "license": "Pexels License",
      "commercial_use": "allowed",
      "file": "artifact://episodes/PD-2026-010-kelo/05_stock/candidates/pexels_i_15263342.jpg",
      "sha256": "sha256:269be61da685ec8e1412121634ff3d77edeb6ae488effdc3bd4dbc0016061e18",
      "bytes": 484343,
      "query": "small house standing alone amid cleared lots",
      "depicts": "small house standing alone amid cleared lots",
      "fetched_at": "",
      "used_in_spans": [
        "SPN-0001"
      ]
    },
    {
      "asset_id": "pexels_i_19378121",
      "asset_type": "image",
      "source": "pexels",
      "source_url": "https://www.pexels.com/photo/lonely-house-on-a-field-19378121/",
      "author": "Jamaal Hutchinson",
      "license": "Pexels License",
      "commercial_use": "allowed",
      "file": "artifact://episodes/PD-2026-010-kelo/05_stock/candidates/pexels_i_19378121.jpg",
      "sha256": "sha256:dfced4fdd526c5d51117c575e7f7c3db487d7dbec3ed438de9d1133a8261c9a8",
      "bytes": 261032,
      "query": "small house standing alone amid cleared lots",
      "depicts": "small house standing alone amid cleared lots",
      "fetched_at": "",
      "used_in_spans": [
        "SPN-0001"
      ]
    },
    {
      "asset_id": "pexels_i_37900459",
      "asset_type": "image",
      "source": "pexels",
      "source_url": "https://www.pexels.com/photo/idyllic-countryside-with-small-houses-and-fields-37900459/",
      "author": "Rahime Gül",
      "license": "Pexels License",
      "commercial_use": "allowed",
      "file": "artifact://episodes/PD-2026-010-kelo/05_stock/candidates/pexels_i_37900459.jpg",
      "sha256": "sha256:f182f6fc97e864ea9884e0e970cfe193d8e72e25e49bdad030c9b60c3b8204e2",
      "bytes": 176787,
      "query": "small house standing alone amid cleared lots",
      "depicts": "small house standing alone amid cleared lots",
      "fetched_at": "",
      "used_in_spans": [
        "SPN-0001"
      ]
    },
    {
      "asset_id": "pixabay_v_78804",
      "asset_type": "video",
      "source": "pixabay",
      "source_url": "https://pixabay.com/videos/id-78804/",
      "author": "ChristianBodhi",
      "license": "Pixabay Content License",
      "commercial_use": "allowed",
      "file": "artifact://episodes/PD-2026-010-kelo/05_stock/candidates/pixabay_v_78804.mp4",
      "sha256": "sha256:67c2a71c5ba13ffdc7ad855f4d3474f3f2cb96ca9323c00aa6417085469baad8",
      "bytes": 1160874,
      "query": "small house standing alone amid cleared lots",
      "depicts": "small house standing alone amid cleared lots",
      "fetched_at": "",
      "used_in_spans": [
        "SPN-0001"
      ]
    },
    {
      "asset_id": "pixabay_v_85109",
      "asset_type": "video",
      "source": "pixabay",
      "source_url": "https://pixabay.com/videos/id-85109/",
      "author": "NickyPe",
      "license": "Pixabay Content License",
      "commercial_use": "allowed",
      "file": "artifact://episodes/PD-2026-010-kelo/05_stock/candidates/pixabay_v_85109.mp4",
      "sha256": "sha256:b4c2e8bdf8fc5b5ae5d5c20a93d756e1f076aad916f86e29f9481a4c5d7ec61e",
      "bytes": 35627576,
      "query": "small house standing alone amid cleared lots",
      "depicts": "small house standing alone amid cleared lots",
      "fetched_at": "",
      "used_in_spans": [
        "SPN-0001"
      ]
    },
    {
      "asset_id": "pixabay_v_16166",
      "asset_type": "video",
      "source": "pixabay",
      "source_url": "https://pixabay.com/videos/id-16166/",
      "author": "anncapictures",
      "license": "Pixabay Content License",
      "commercial_use": "allowed",
      "file": "artifact://episodes/PD-2026-010-kelo/05_stock/candidates/pixabay_v_16166.mp4",
      "sha256": "sha256:db23942d080c2d662dedd6f40310fe4ff02b76f1f0278d318893ecf1f06bd5ca",
      "bytes": 2803642,
      "query": "small house standing alone amid cleared lots",
      "depicts": "small house standing alone amid cleared lots",
      "fetched_at": "",
      "used_in_spans": [
        "SPN-0001"
      ]
    },
    {
      "asset_id": "pixabay_i_7783664",
      "asset_type": "image",
      "source": "pixabay",
      "source_url": "https://pixabay.com/photos/birds-seagulls-lot-lake-frozen-7783664/",
      "author": "Surprising_Media",
      "license": "Pixabay Content License",
      "commercial_use": "allowed",
      "file": "artifact://episodes/PD-2026-010-kelo/05_stock/candidates/pixabay_i_7783664.jpg",
      "sha256": "sha256:274e4ef6e11fc645d6e0ad3750f7229a8f72511477e01fc898a5e7c82593fc9b",
      "bytes": 418699,
      "query": "small house standing alone amid cleared lots",
      "depicts": "small house standing alone amid cleared lots",
      "fetched_at": "",
      "used_in_spans": [
        "SPN-0001"
      ]
    },
    {
      "asset_id": "pixabay_i_2666433",
      "asset_type": "image",
      "source": "pixabay",
      "source_url": "https://pixabay.com/photos/woman-alone-crowd-sad-depressed-2666433/",
      "author": "Graehawk",
      "license": "Pixabay Content License",
      "commercial_use": "allowed",
      "file": "artifact://episodes/PD-2026-010-kelo/05_stock/candidates/pixabay_i_2666433.jpg",
      "sha256": "sha256:ab5729bf5dd7f3565f2ac8924a096d44569f926cfdda8d4b89f8e9a4bff3e28c",
      "bytes": 347469,
      "query": "small house standing alone amid cleared lots",
      "depicts": "small house standing alone amid cleared lots",
      "fetched_at": "",
      "used_in_spans": [
        "SPN-0001"
      ]
    },
    {
      "asset_id": "pixabay_i_1869914",
      "asset_type": "image",
      "source": "pixabay",
      "source_url": "https://pixabay.com/photos/alone-feet-shoes-laces-sneakers-1869914/",
      "author": "Pexels",
      "license": "Pixabay Content License",
      "commercial_use": "allowed",
      "file": "artifact://episodes/PD-2026-010-kelo/05_stock/candidates/pixabay_i_1869914.jpg",
      "sha256": "sha256:956a3e38057bf8ca2623c65ab6ea3590d16729c5a207a729c3eb2b4628e24817",
      "bytes": 223405,
      "query": "small house standing alone amid cleared lots",
      "depicts": "small house standing alone amid cleared lots",
      "fetched_at": "",
      "used_in_spans": [
        "SPN-0001"
      ]
    },
    {
      "asset_id": "pexels_v_17362431",
      "asset_type": "video",
      "source": "pexels",
      "source_url": "https://www.pexels.com/video/drone-flight-over-bird-key-in-sarasota-17362431/",
      "author": "Dmytro Kramarenko",
      "license": "Pexels License",
      "commercial_use": "allowed",
      "file": "artifact://episodes/PD-2026-010-kelo/05_stock/candidates/pexels_v_17362431.mp4",
      "sha256": "sha256:64630537242807e487dcbc766b60c8b0a29bf9ea8f2049ba1d9e1ddcdba3e38e",
      "bytes": 7726349,
      "query": "Establishing: a modest waterfront neighborhood",
      "depicts": "Establishing: a modest waterfront neighborhood",
      "fetched_at": "",
      "used_in_spans": [
        "SPN-0003"
      ]
    },
    {
      "asset_id": "pexels_v_3858852",
      "asset_type": "video",
      "source": "pexels",
      "source_url": "https://www.pexels.com/video/drone-footage-of-a-luxurious-lake-community-3858852/",
      "author": "K",
      "license": "Pexels License",
      "commercial_use": "allowed",
      "file": "artifact://episodes/PD-2026-010-kelo/05_stock/candidates/pexels_v_3858852.mp4",
      "sha256": "sha256:850d3efeff0e9f87a176204e7bed0691451ea78349f0a63e891d9efacca3d3f0",
      "bytes": 23685446,
      "query": "Establishing: a modest waterfront neighborhood",
      "depicts": "Establishing: a modest waterfront neighborhood",
      "fetched_at": "",
      "used_in_spans": [
        "SPN-0003"
      ]
    },
    {
      "asset_id": "pexels_v_3859473",
      "asset_type": "video",
      "source": "pexels",
      "source_url": "https://www.pexels.com/video/aerial-shot-of-a-village-in-the-river-3859473/",
      "author": "K",
      "license": "Pexels License",
      "commercial_use": "allowed",
      "file": "artifact://episodes/PD-2026-010-kelo/05_stock/candidates/pexels_v_3859473.mp4",
      "sha256": "sha256:3d1d314f048f3bf73dbc1190ea119517a28e0873ae273ef2f861c795f671e565",
      "bytes": 20403690,
      "query": "Establishing: a modest waterfront neighborhood",
      "depicts": "Establishing: a modest waterfront neighborhood",
      "fetched_at": "",
      "used_in_spans": [
        "SPN-0003"
      ]
    },
    {
      "asset_id": "pexels_i_20270908",
      "asset_type": "image",
      "source": "pexels",
      "source_url": "https://www.pexels.com/photo/bungalows-over-the-lake-20270908/",
      "author": "Robert So",
      "license": "Pexels License",
      "commercial_use": "allowed",
      "file": "artifact://episodes/PD-2026-010-kelo/05_stock/candidates/pexels_i_20270908.jpg",
      "sha256": "sha256:c9e5e59f8f400b145490a60f4d405e871da7981d0f4d399b9383dca0970d6e50",
      "bytes": 237308,
      "query": "Establishing: a modest waterfront neighborhood",
      "depicts": "Establishing: a modest waterfront neighborhood",
      "fetched_at": "",
      "used_in_spans": [
        "SPN-0003"
      ]
    },
    {
      "asset_id": "pexels_i_37097738",
      "asset_type": "image",
      "source": "pexels",
      "source_url": "https://www.pexels.com/photo/serene-lakeside-homes-at-dusk-reflection-37097738/",
      "author": "Cara Denison",
      "license": "Pexels License",
      "commercial_use": "allowed",
      "file": "artifact://episodes/PD-2026-010-kelo/05_stock/candidates/pexels_i_37097738.jpg",
      "sha256": "sha256:5df4648d20a1e07084f8a0359a4956d801ec3e215391d67bd6ab69d74507c366",
      "bytes": 218387,
      "query": "Establishing: a modest waterfront neighborhood",
      "depicts": "Establishing: a modest waterfront neighborhood",
      "fetched_at": "",
      "used_in_spans": [
        "SPN-0003"
      ]
    },
    {
      "asset_id": "pexels_i_3845102",
      "asset_type": "image",
      "source": "pexels",
      "source_url": "https://www.pexels.com/photo/aerial-view-of-houses-near-body-of-water-3845102/",
      "author": "K",
      "license": "Pexels License",
      "commercial_use": "allowed",
      "file": "artifact://episodes/PD-2026-010-kelo/05_stock/candidates/pexels_i_3845102.jpg",
      "sha256": "sha256:9c288b6bc825f9cba444c879b2874dcfce7f58a5eb3a2de37c68270c4ce22a39",
      "bytes": 401080,
      "query": "Establishing: a modest waterfront neighborhood",
      "depicts": "Establishing: a modest waterfront neighborhood",
      "fetched_at": "",
      "used_in_spans": [
        "SPN-0003"
      ]
    },
    {
      "asset_id": "pexels_v_8206441",
      "asset_type": "video",
      "source": "pexels",
      "source_url": "https://www.pexels.com/video/little-girls-playing-with-a-dollhouse-8206441/",
      "author": "Ron Lach",
      "license": "Pexels License",
      "commercial_use": "allowed",
      "file": "artifact://episodes/PD-2026-010-kelo/05_stock/candidates/pexels_v_8206441.mp4",
      "sha256": "sha256:72d8c5f47da3f02c0fa96a84b884d5467c94a9f8710c5de303daeb5bc79113e7",
      "bytes": 4574689,
      "query": "little pink house",
      "depicts": "little pink house",
      "fetched_at": "",
      "used_in_spans": [
        "SPN-0004"
      ]
    },
    {
      "asset_id": "pexels_v_36212672",
      "asset_type": "video",
      "source": "pexels",
      "source_url": "https://www.pexels.com/video/charming-pink-cottage-amidst-lush-greenery-36212672/",
      "author": "Henrique Feiten",
      "license": "Pexels License",
      "commercial_use": "allowed",
      "file": "artifact://episodes/PD-2026-010-kelo/05_stock/candidates/pexels_v_36212672.mp4",
      "sha256": "sha256:c4ea7021038c93e6378e0604e5b05c3adcc5a93071ee4f26038c14def92a4311",
      "bytes": 5779628,
      "query": "little pink house",
      "depicts": "little pink house",
      "fetched_at": "",
      "used_in_spans": [
        "SPN-0004"
      ]
    },
    {
      "asset_id": "pexels_v_8206435",
      "asset_type": "video",
      "source": "pexels",
      "source_url": "https://www.pexels.com/video/little-girls-playing-with-soft-toys-8206435/",
      "author": "Ron Lach",
      "license": "Pexels License",
      "commercial_use": "allowed",
      "file": "artifact://episodes/PD-2026-010-kelo/05_stock/candidates/pexels_v_8206435.mp4",
      "sha256": "sha256:96491ec4e8ed792681808a269de564ea5fafb7c00c29144cb80480ca9bc2c2fd",
      "bytes": 27212065,
      "query": "little pink house",
      "depicts": "little pink house",
      "fetched_at": "",
      "used_in_spans": [
        "SPN-0004"
      ]
    },
    {
      "asset_id": "pexels_i_4389714",
      "asset_type": "image",
      "source": "pexels",
      "source_url": "https://www.pexels.com/photo/old-housing-complex-under-bright-blue-sky-4389714/",
      "author": "ric perin",
      "license": "Pexels License",
      "commercial_use": "allowed",
      "file": "artifact://episodes/PD-2026-010-kelo/05_stock/candidates/pexels_i_4389714.jpg",
      "sha256": "sha256:0e4b3ee68dc1b2c196fa1706d36cf9b997a466fc15dc60b411faa934f209b71d",
      "bytes": 350049,
      "query": "little pink house",
      "depicts": "little pink house",
      "fetched_at": "",
      "used_in_spans": [
        "SPN-0004"
      ]
    },
    {
      "asset_id": "pexels_i_3961748",
      "asset_type": "image",
      "source": "pexels",
      "source_url": "https://www.pexels.com/photo/miniature-clay-house-in-white-background-3961748/",
      "author": "Andreea Ch",
      "license": "Pexels License",
      "commercial_use": "allowed",
      "file": "artifact://episodes/PD-2026-010-kelo/05_stock/candidates/pexels_i_3961748.jpg",
      "sha256": "sha256:5e6b2dc9333ba0d0a54f384de3189b13188614a7e2fb73a1d098a6cc009806f3",
      "bytes": 36456,
      "query": "little pink house",
      "depicts": "little pink house",
      "fetched_at": "",
      "used_in_spans": [
        "SPN-0004"
      ]
    },
    {
      "asset_id": "pexels_i_16553771",
      "asset_type": "image",
      "source": "pexels",
      "source_url": "https://www.pexels.com/photo/a-pink-house-by-the-sea-16553771/",
      "author": "Robert So",
      "license": "Pexels License",
      "commercial_use": "allowed",
      "file": "artifact://episodes/PD-2026-010-kelo/05_stock/candidates/pexels_i_16553771.jpg",
      "sha256": "sha256:75d0c186c0104b54b9ad4bb62a6eef173e81b9069d93a6237c13e24fafec21f7",
      "bytes": 364927,
      "query": "little pink house",
      "depicts": "little pink house",
      "fetched_at": "",
      "used_in_spans": [
        "SPN-0004"
      ]
    },
    {
      "asset_id": "pixabay_v_230060",
      "asset_type": "video",
      "source": "pixabay",
      "source_url": "https://pixabay.com/videos/id-230060/",
      "author": "adege",
      "license": "Pixabay Content License",
      "commercial_use": "allowed",
      "file": "artifact://episodes/PD-2026-010-kelo/05_stock/candidates/pixabay_v_230060.mp4",
      "sha256": "sha256:1c33f804bdf22c2c498b008fc1a5ea16fd44065ecc52cd0864d34d48d9f191ef",
      "bytes": 10924006,
      "query": "little pink house",
      "depicts": "little pink house",
      "fetched_at": "",
      "used_in_spans": [
        "SPN-0004"
      ]
    },
    {
      "asset_id": "pixabay_v_34573",
      "asset_type": "video",
      "source": "pixabay",
      "source_url": "https://pixabay.com/videos/id-34573/",
      "author": "SooYeongBeh",
      "license": "Pixabay Content License",
      "commercial_use": "allowed",
      "file": "artifact://episodes/PD-2026-010-kelo/05_stock/candidates/pixabay_v_34573.mp4",
      "sha256": "sha256:31aff5304e262848844479921331933d9586d51d7fc490b52432a50af181c9a0",
      "bytes": 13264995,
      "query": "little pink house",
      "depicts": "little pink house",
      "fetched_at": "",
      "used_in_spans": [
        "SPN-0004"
      ]
    },
    {
      "asset_id": "pixabay_v_163869",
      "asset_type": "video",
      "source": "pixabay",
      "source_url": "https://pixabay.com/videos/id-163869/",
      "author": "KIMDAEJEUNG",
      "license": "Pixabay Content License",
      "commercial_use": "allowed",
      "file": "artifact://episodes/PD-2026-010-kelo/05_stock/candidates/pixabay_v_163869.mp4",
      "sha256": "sha256:bca64f063ccc86514b3402a85417570051fb1968ee9ff9dae20124a35914cbab",
      "bytes": 46019951,
      "query": "little pink house",
      "depicts": "little pink house",
      "fetched_at": "",
      "used_in_spans": [
        "SPN-0004"
      ]
    },
    {
      "asset_id": "pixabay_i_2047596",
      "asset_type": "image",
      "source": "pixabay",
      "source_url": "https://pixabay.com/photos/booties-baby-girl-clothes-pink-2047596/",
      "author": "TerriC",
      "license": "Pixabay Content License",
      "commercial_use": "allowed",
      "file": "artifact://episodes/PD-2026-010-kelo/05_stock/candidates/pixabay_i_2047596.jpg",
      "sha256": "sha256:061bfeb3019f981d1ebc4c82aedd0edde3ffaac643ae99b38a708f354f7b3c57",
      "bytes": 223746,
      "query": "little pink house",
      "depicts": "little pink house",
      "fetched_at": "",
      "used_in_spans": [
        "SPN-0004"
      ]
    },
    {
      "asset_id": "pixabay_i_1839623",
      "asset_type": "image",
      "source": "pixabay",
      "source_url": "https://pixabay.com/photos/girl-grass-nature-summer-cute-1839623/",
      "author": "Pexels",
      "license": "Pixabay Content License",
      "commercial_use": "allowed",
      "file": "artifact://episodes/PD-2026-010-kelo/05_stock/candidates/pixabay_i_1839623.jpg",
      "sha256": "sha256:ec898f56127ec540cdc40d0e3b198944ffc30ba3778a078e2aa5e72704cca64f",
      "bytes": 218823,
      "query": "little pink house",
      "depicts": "little pink house",
      "fetched_at": "",
      "used_in_spans": [
        "SPN-0004"
      ]
    },
    {
      "asset_id": "pixabay_i_6706970",
      "asset_type": "image",
      "source": "pixabay",
      "source_url": "https://pixabay.com/photos/boy-child-shelter-house-kid-6706970/",
      "author": "mostafa_meraji",
      "license": "Pixabay Content License",
      "commercial_use": "allowed",
      "file": "artifact://episodes/PD-2026-010-kelo/05_stock/candidates/pixabay_i_6706970.jpg",
      "sha256": "sha256:286792bf23cb816f9eeae8842a1c0b8602760cd3334f26d2b2748bea0aada6bc",
      "bytes": 526686,
      "query": "little pink house",
      "depicts": "little pink house",
      "fetched_at": "",
      "used_in_spans": [
        "SPN-0004"
      ]
    },
    {
      "asset_id": "pexels_v_30160486",
      "asset_type": "video",
      "source": "pexels",
      "source_url": "https://www.pexels.com/video/aerial-view-of-suburban-construction-site-30160486/",
      "author": "K",
      "license": "Pexels License",
      "commercial_use": "allowed",
      "file": "artifact://episodes/PD-2026-010-kelo/05_stock/candidates/pexels_v_30160486.mp4",
      "sha256": "sha256:20fdfd1e03c6093e11cb38f82222b4aa8ba4a42a47d3bf30b633d1aa217e4b3e",
      "bytes": 30049718,
      "query": "empty cleared lot where homes once stood",
      "depicts": "empty cleared lot where homes once stood",
      "fetched_at": "",
      "used_in_spans": [
        "SPN-0020"
      ]
    },
    {
      "asset_id": "pexels_v_34668482",
      "asset_type": "video",
      "source": "pexels",
      "source_url": "https://www.pexels.com/video/aerial-view-of-suburban-development-area-34668482/",
      "author": "Michael",
      "license": "Pexels License",
      "commercial_use": "allowed",
      "file": "artifact://episodes/PD-2026-010-kelo/05_stock/candidates/pexels_v_34668482.mp4",
      "sha256": "sha256:1c5e7ef3b05346b28805b0724f0df847b56a3ad547c04cd5f7cd1b64c80bd2e9",
      "bytes": 9001498,
      "query": "empty cleared lot where homes once stood",
      "depicts": "empty cleared lot where homes once stood",
      "fetched_at": "",
      "used_in_spans": [
        "SPN-0020"
      ]
    },
    {
      "asset_id": "pexels_v_31731560",
      "asset_type": "video",
      "source": "pexels",
      "source_url": "https://www.pexels.com/video/aerial-view-of-suburban-residential-development-31731560/",
      "author": "Salman Ahmad",
      "license": "Pexels License",
      "commercial_use": "allowed",
      "file": "artifact://episodes/PD-2026-010-kelo/05_stock/candidates/pexels_v_31731560.mp4",
      "sha256": "sha256:12f78da56b37fea3c8c3bc549f8aa829ddb24263db5f5a69b1049c71631a0bd8",
      "bytes": 15904601,
      "query": "empty cleared lot where homes once stood",
      "depicts": "empty cleared lot where homes once stood",
      "fetched_at": "",
      "used_in_spans": [
        "SPN-0020"
      ]
    },
    {
      "asset_id": "pexels_i_37738120",
      "asset_type": "image",
      "source": "pexels",
      "source_url": "https://www.pexels.com/photo/empty-urban-lot-with-buildings-and-trees-37738120/",
      "author": "Mehmet Turgut  Kirkgoz",
      "license": "Pexels License",
      "commercial_use": "allowed",
      "file": "artifact://episodes/PD-2026-010-kelo/05_stock/candidates/pexels_i_37738120.jpg",
      "sha256": "sha256:9b86561733bb2a7c4c38213f9dc465e57f82496ecd924642da64bd21a06eafed",
      "bytes": 180180,
      "query": "empty cleared lot where homes once stood",
      "depicts": "empty cleared lot where homes once stood",
      "fetched_at": "",
      "used_in_spans": [
        "SPN-0020"
      ]
    },
    {
      "asset_id": "pexels_i_17602526",
      "asset_type": "image",
      "source": "pexels",
      "source_url": "https://www.pexels.com/photo/an-empty-field-and-modern-apartment-buildings-17602526/",
      "author": "David Brown",
      "license": "Pexels License",
      "commercial_use": "allowed",
      "file": "artifact://episodes/PD-2026-010-kelo/05_stock/candidates/pexels_i_17602526.jpg",
      "sha256": "sha256:e5890256976fddb451959de813b7bf15a53f6e3906dec9441f5774f0d8deaa4e",
      "bytes": 443606,
      "query": "empty cleared lot where homes once stood",
      "depicts": "empty cleared lot where homes once stood",
      "fetched_at": "",
      "used_in_spans": [
        "SPN-0020"
      ]
    },
    {
      "asset_id": "pexels_i_33043393",
      "asset_type": "image",
      "source": "pexels",
      "source_url": "https://www.pexels.com/photo/new-home-construction-in-elk-grove-california-33043393/",
      "author": "D Goug",
      "license": "Pexels License",
      "commercial_use": "allowed",
      "file": "artifact://episodes/PD-2026-010-kelo/05_stock/candidates/pexels_i_33043393.jpg",
      "sha256": "sha256:55acc202db8fe80fd4ff1994addf74820e668af9a8b477b657e2fb6ac500491d",
      "bytes": 328680,
      "query": "empty cleared lot where homes once stood",
      "depicts": "empty cleared lot where homes once stood",
      "fetched_at": "",
      "used_in_spans": [
        "SPN-0020"
      ]
    },
    {
      "asset_id": "pixabay_v_149975",
      "asset_type": "video",
      "source": "pixabay",
      "source_url": "https://pixabay.com/videos/id-149975/",
      "author": "julientromeur",
      "license": "Pixabay Content License",
      "commercial_use": "allowed",
      "file": "artifact://episodes/PD-2026-010-kelo/05_stock/candidates/pixabay_v_149975.mp4",
      "sha256": "sha256:4a79abc0b11e6aa7070e671246a0d21ae66c2c6c3af440f72c351a8df6facf1e",
      "bytes": 516792,
      "query": "empty cleared lot where homes once stood",
      "depicts": "empty cleared lot where homes once stood",
      "fetched_at": "",
      "used_in_spans": [
        "SPN-0020"
      ]
    },
    {
      "asset_id": "pixabay_v_10551",
      "asset_type": "video",
      "source": "pixabay",
      "source_url": "https://pixabay.com/videos/id-10551/",
      "author": "carl_watermark",
      "license": "Pixabay Content License",
      "commercial_use": "allowed",
      "file": "artifact://episodes/PD-2026-010-kelo/05_stock/candidates/pixabay_v_10551.mp4",
      "sha256": "sha256:45252f1b847bc909916ebb3d7e2ce1095c872b17354a4b142dbffc5bf6e20778",
      "bytes": 1038263,
      "query": "empty cleared lot where homes once stood",
      "depicts": "empty cleared lot where homes once stood",
      "fetched_at": "",
      "used_in_spans": [
        "SPN-0020"
      ]
    },
    {
      "asset_id": "pixabay_v_55568",
      "asset_type": "video",
      "source": "pixabay",
      "source_url": "https://pixabay.com/videos/id-55568/",
      "author": "tommyvideo",
      "license": "Pixabay Content License",
      "commercial_use": "allowed",
      "file": "artifact://episodes/PD-2026-010-kelo/05_stock/candidates/pixabay_v_55568.mp4",
      "sha256": "sha256:f1726c2de8cff3eba387b9b654ba6785915fbb17cf8f6fa7a3fc831c3e73c215",
      "bytes": 1409403,
      "query": "empty cleared lot where homes once stood",
      "depicts": "empty cleared lot where homes once stood",
      "fetched_at": "",
      "used_in_spans": [
        "SPN-0020"
      ]
    },
    {
      "asset_id": "pixabay_i_6538926",
      "asset_type": "image",
      "source": "pixabay",
      "source_url": "https://pixabay.com/photos/parking-lot-underground-garage-6538926/",
      "author": "quangnaruto",
      "license": "Pixabay Content License",
      "commercial_use": "allowed",
      "file": "artifact://episodes/PD-2026-010-kelo/05_stock/candidates/pixabay_i_6538926.jpg",
      "sha256": "sha256:304172a834193bfe91c4a69cb6f27c9f31d77b4674de0f6383c62f5cea8040d9",
      "bytes": 146102,
      "query": "empty cleared lot where homes once stood",
      "depicts": "empty cleared lot where homes once stood",
      "fetched_at": "",
      "used_in_spans": [
        "SPN-0020"
      ]
    },
    {
      "asset_id": "pixabay_i_1834446",
      "asset_type": "image",
      "source": "pixabay",
      "source_url": "https://pixabay.com/photos/brick-wall-empty-lighted-night-1834446/",
      "author": "Pexels",
      "license": "Pixabay Content License",
      "commercial_use": "allowed",
      "file": "artifact://episodes/PD-2026-010-kelo/05_stock/candidates/pixabay_i_1834446.jpg",
      "sha256": "sha256:077f713be1934254a4b6492e97b01b485429c3ff795fb53fbb89487d3e449288",
      "bytes": 355126,
      "query": "empty cleared lot where homes once stood",
      "depicts": "empty cleared lot where homes once stood",
      "fetched_at": "",
      "used_in_spans": [
        "SPN-0020"
      ]
    },
    {
      "asset_id": "pixabay_i_565914",
      "asset_type": "image",
      "source": "pixabay",
      "source_url": "https://pixabay.com/photos/glass-bottle-empty-wine-glass-565914/",
      "author": "Yummymoon",
      "license": "Pixabay Content License",
      "commercial_use": "allowed",
      "file": "artifact://episodes/PD-2026-010-kelo/05_stock/candidates/pixabay_i_565914.jpg",
      "sha256": "sha256:2b73c71068ad17c0f1f9c0a8743d92cbc011c5c60bcc700417cac116d073de45",
      "bytes": 156886,
      "query": "empty cleared lot where homes once stood",
      "depicts": "empty cleared lot where homes once stood",
      "fetched_at": "",
      "used_in_spans": [
        "SPN-0020"
      ]
    }
  ]
}